rcfd_pcg/__init__.py
rcfd_pcg/ablate.py
rcfd_pcg/bench.py
rcfd_pcg/cli.py
rcfd_pcg/datasets.py
rcfd_pcg/env.py
rcfd_pcg/gpu.py
rcfd_pcg/linop.py
rcfd_pcg/rcfd.py
rcfd_pcg/sklearn.py
rcfd_pcg/suite.py
rcfd_pcg/torch_api.py
rcfd_pcg/util.py
rcfd_pcg-0.1.0.dist-info/METADATA
rcfd_pcg-0.1.0.dist-info/WHEEL
rcfd_pcg-0.1.0.dist-info/entry_points.txt
rcfd_pcg-0.1.0.dist-info/top_level.txt
rcfd_pcg-0.1.0.dist-info/RECORD
