Metadata-Version: 2.4
Name: rcfd-pcg
Version: 0.1.0
Summary: RCFD-PCG: Ridge-Corrected Frequent-Directions Preconditioned Conjugate Gradient
Author: RCFD Team
License-Expression: MIT
Requires-Python: >=3.9
Requires-Dist: numpy>=1.23
Requires-Dist: scipy>=1.9
Requires-Dist: threadpoolctl>=3.1.0
Provides-Extra: dev
Requires-Dist: black==24.4.2; extra == "dev"
Requires-Dist: ruff==0.5.5; extra == "dev"
Requires-Dist: isort==5.13.2; extra == "dev"
Requires-Dist: pytest>=7; extra == "dev"
